LICENSE.txt
MANIFEST.in
README.md
setup.cfg
setup.py
silvair_uart_decoder/__init__.py
silvair_uart_decoder/main.py
silvair_uart_decoder.egg-info/PKG-INFO
silvair_uart_decoder.egg-info/SOURCES.txt
silvair_uart_decoder.egg-info/dependency_links.txt
silvair_uart_decoder.egg-info/entry_points.txt
silvair_uart_decoder.egg-info/requires.txt
silvair_uart_decoder.egg-info/top_level.txt
silvair_uart_decoder/LogicExtension/__init__.py
silvair_uart_decoder/LogicExtension/extension.json
silvair_uart_decoder/LogicExtension/source_template/SilvairUARTExtension.py_template
silvair_uart_decoder/LogicExtension/source_template/__init__.py
silvair_uart_decoder/input_converters/__init__.py
silvair_uart_decoder/input_converters/default_converter.py
silvair_uart_decoder/input_converters/extension_converter.py
silvair_uart_decoder/input_converters/input_converter.py
silvair_uart_decoder/input_converters/saleae_converter.py
silvair_uart_decoder/input_converters/silvair_uart_state_machine.py
silvair_uart_decoder/input_converters/test_uart_proto_frame.py
silvair_uart_decoder/input_converters/uart_proto_frame.py
silvair_uart_decoder/uart_protocol/__init__.py
silvair_uart_decoder/uart_protocol/adapters.py
silvair_uart_decoder/uart_protocol/common.py
silvair_uart_decoder/uart_protocol/formatters.py
silvair_uart_decoder/uart_protocol/parsers.py
silvair_uart_decoder/uart_protocol/test_parsers.py