Metadata-Version: 2.1
Name: silvair-uart-decoder
Version: 0.1.4
Summary: Tool for decoding Silvair UART protocol.
Home-page: https://github.com/SilvairGit/silvair-uart-decoder
Author: Silvair
Author-email: support@silvair.com
License: MIT
Platform: UNKNOWN
License-File: LICENSE.txt
